hcl2/__init__.py
hcl2/__main__.py
hcl2/api.py
hcl2/builder.py
hcl2/const.py
hcl2/hcl2.lark
hcl2/parser.py
hcl2/py.typed
hcl2/reconstructor.py
hcl2/transformer.py
hcl2/version.py
python_hcl2-7.3.0.dist-info/licenses/LICENSE
python_hcl2-7.3.0.dist-info/METADATA
python_hcl2-7.3.0.dist-info/WHEEL
python_hcl2-7.3.0.dist-info/entry_points.txt
python_hcl2-7.3.0.dist-info/top_level.txt
python_hcl2-7.3.0.dist-info/RECORD
